insight/__init__.py
insight/check.py
insight/plot.py
insight/py.typed
insight/version.py
insight/alembic/README
insight/alembic/alembic.ini
insight/alembic/env.py
insight/alembic/main.py
insight/alembic/script.py.mako
insight/alembic/versions/495f69cbfe6d_add_result_sub_run.py
insight/alembic/versions/512d9168f6c2_add_metric_name_unique_constraint.py
insight/alembic/versions/9aca5ae68ff5_add_initial_tables.py
insight/alembic/versions/a2198ae60b44_added_version_name_unique_constaint.py
insight/alembic/versions/d2198fd60b0e_added_result_run_id.py
insight/alembic/versions/eaf7bb3598af_version_unique_constraint.py
insight/database/__init__.py
insight/database/schema.py
insight/database/utils.py
insight/fonts/SourceSansPro-Regular.ttf
insight/metrics/__init__.py
insight/metrics/base.py
insight/metrics/confidence_interval.py
insight/metrics/metrics.py
insight/metrics/metrics_usage.py
insight/metrics/utils.py
insight-1.0.dist-info/LICENSE.md
insight-1.0.dist-info/METADATA
insight-1.0.dist-info/WHEEL
insight-1.0.dist-info/entry_points.txt
insight-1.0.dist-info/top_level.txt
insight-1.0.dist-info/RECORD
