Metadata-Version: 2.1
Name: insight
Version: 1.0
Summary: A python library for monitoring, comparing and extracting insights from data.
Author-email: "Synthesized Ltd." <ml@synthesized.io>, Daniel Sabanov <daniel@sadogursky.com>, Simon Swan <shk.swan@gmail.com>
License: BSD 3-Clause License
Project-URL: homepage, https://github.com/synthesized-io/insight
Project-URL: documentation, https://docs.synthesized.io/
Project-URL: repository, https://github.com/synthesized-io/insight
Keywords: metrics,data,evaluation
Platform: MacOS
Platform: Windows
Platform: Linux
Classifier: Development Status :: 4 - Beta
Classifier: License :: OSI Approved :: BSD License
Classifier: Intended Audience :: Developers
Classifier: Intended Audience :: Science/Research
Classifier: Operating System :: MacOS
Classifier: Operating System :: Microsoft :: Windows
Classifier: Operating System :: Unix
Classifier: Programming Language :: Python :: 3
Classifier: Programming Language :: Python :: 3.8
Classifier: Programming Language :: Python :: 3.9
Classifier: Programming Language :: Python :: 3.10
Classifier: Topic :: Scientific/Engineering
Requires-Python: >=3.8
License-File: LICENSE.md
Requires-Dist: matplotlib >=3.4
Requires-Dist: numpy >=1.18
Requires-Dist: pandas >=1.2
Requires-Dist: scipy >=1.5
Requires-Dist: seaborn >=0.11.0
Requires-Dist: cachetools >=5.0
Provides-Extra: db
Requires-Dist: alembic ; extra == 'db'
Requires-Dist: sqlalchemy >=2.0 ; extra == 'db'
Requires-Dist: psycopg2 >=2.9 ; (platform_machine != "arm64" or platform_system != "Darwin") and extra == 'db'
Requires-Dist: psycopg2-binary >=2.9 ; (platform_machine == "arm64" or platform_system == "Darwin") and extra == 'db'
Provides-Extra: dev
Requires-Dist: pre-commit ; extra == 'dev'
Requires-Dist: pylint ; extra == 'dev'
Provides-Extra: test
Requires-Dist: pytest ; extra == 'test'
Requires-Dist: pytest-cov ; extra == 'test'
